{
    "title": "Më përkrahni duke votuar!",
    "description": {
        "1": "Është si të na japësh para pa dhënë asnjë lekë! Na mbështesni me një [votim të shpejtë në top.gg]({url}), kjo i lejon njerëzit të gjejnë më lehtë {name}, faleminderit për mbështetjen tuaj!",
        "2": "Votimi për mua do t'ju lejojë qasje në disa kufij më të lartë në disa vende dhe një [roli i votuesit në serverin tonë të komunitetit]({url}) për 12 orët e ardhshme!"
    },
    "already": "ju keni votuar tashmë sot, kthehuni {time} për të votuar përsëri!"
}